segno_plugin.py
qrcode_other_pattern-0.0.3.dist-info/METADATA
qrcode_other_pattern-0.0.3.dist-info/WHEEL
qrcode_other_pattern-0.0.3.dist-info/entry_points.txt
qrcode_other_pattern-0.0.3.dist-info/top_level.txt
qrcode_other_pattern-0.0.3.dist-info/RECORD
