Metadata-Version: 2.1
Name: qrcode-other-pattern
Version: 0.0.3
Author-email: Ferdinand Silva <ferdinandsilva@ferdinandsilva.com>
Project-URL: Home, https://github.com/six519/qrcode-other-pattern
Classifier: Intended Audience :: Developers
Classifier: Natural Language :: English
Classifier: Programming Language :: Python
Classifier: Programming Language :: Python :: 3
Classifier: Topic :: Software Development :: Libraries :: Python Modules
Requires-Python: >=3.6
Requires-Dist: segno >=1.6.1
Requires-Dist: Pillow >=10.4.0
